Dit/__init__.py
Dit/core.py
dbdit-0.0.1.dist-info/LICENSE
dbdit-0.0.1.dist-info/METADATA
dbdit-0.0.1.dist-info/WHEEL
dbdit-0.0.1.dist-info/entry_points.txt
dbdit-0.0.1.dist-info/top_level.txt
dbdit-0.0.1.dist-info/RECORD
