Metadata-Version: 2.1
Name: dbdit
Version: 0.0.1
Summary: Version control for Databases
Home-page: https://github.com/sr2echa/dit
Author: Sreecharan S, Harish Chandran, Harish Barathi, Nidish TS
Classifier: Programming Language :: Python :: 3
Classifier: License :: OSI Approved :: MIT License
Classifier: Operating System :: OS Independent
Requires-Python: >=3.6
License-File: LICENSE
Requires-Dist: setuptools
Requires-Dist: mysql-connector-python
Requires-Dist: rich-click
Requires-Dist: rich
Requires-Dist: questionary
Requires-Dist: Flask
Requires-Dist: requests
